say_hello.py
setup.py
ye_python.egg-info/PKG-INFO
ye_python.egg-info/SOURCES.txt
ye_python.egg-info/dependency_links.txt
ye_python.egg-info/requires.txt
ye_python.egg-info/top_level.txt