Metadata-Version: 1.0
Name: ye-python
Version: 0.1
Summary: This is an Example Package
Home-page: http://example.com/HelloWorld/
Author: Yecss
Author-email: 2078136028@qq.com
License: PSF
Keywords: hello world example examples
Platform: UNKNOWN
